<?xml version="1.0" encoding="utf-8" ?>
<Status>
	<Status StateCode="AL" StateName="Alabama" />
	<Status StateCode="AK" StateName="Alaska" />
	<Status StateCode="AZ" StateName="Arizona" />
	<Status StateCode="AR" StateName="Arkansas" />
	<Status StateCode="CA" StateName="California" />
	<Status StateCode="CO" StateName="Colorado" />
	<Status StateCode="CT" StateName="Connecticut" />
	<Status StateCode="DE" StateName="Delaware" />
	<Status StateCode="DC" StateName="District of Columbia" />
	<Status StateCode="FL" StateName="Florida" />
	<Status StateCode="GA" StateName="Georgia" />
	<Status StateCode="HI" StateName="Hawaii" />
	<Status StateCode="ID" StateName="Idaho" />
	<Status StateCode="IL" StateName="Illinois" />
	<Status StateCode="IN" StateName="Indiana" />
	<Status StateCode="IA" StateName="Iowa" />
	<Status StateCode="KS" StateName="Kansas" />
	<Status StateCode="KY" StateName="Kentucky" />
	<Status StateCode="LA" StateName="Louisiana" />
	<Status StateCode="ME" StateName="Maine" />
	<Status StateCode="MD" StateName="Maryland" />
	<Status StateCode="MA" StateName="Massachusetts" />
	<Status StateCode="MI" StateName="Michigan" />
	<Status StateCode="MN" StateName="Minnesota" />
	<Status StateCode="MS" StateName="Mississippi" />
	<Status StateCode="MO" StateName="Missouri" />
	<Status StateCode="MT" StateName="Montana" />
	<Status StateCode="NE" StateName="Nebraska" />
	<Status StateCode="NV" StateName="Nevada" />
	<Status StateCode="NH" StateName="New Hampshire" />
	<Status StateCode="NJ" StateName="New Jersey" />
	<Status StateCode="NM" StateName="New Mexico" />
	<Status StateCode="NY" StateName="New York" />
	<Status StateCode="NC" StateName="North Carolina" />
	<Status StateCode="ND" StateName="North Dakota" />
	<Status StateCode="OH" StateName="Ohio" />
	<Status StateCode="OK" StateName="Oklahoma" />
	<Status StateCode="OR" StateName="Oregon" />
	<Status StateCode="PA" StateName="Pennsylvania" />
	<Status StateCode="RI" StateName="Rhode Island" />
	<Status StateCode="SC" StateName="South Carolina" />
	<Status StateCode="SD" StateName="South Dakota" />
	<Status StateCode="TN" StateName="Tennessee" />
	<Status StateCode="TX" StateName="Texas" />
	<Status StateCode="UT" StateName="Utah" />
	<Status StateCode="VT" StateName="Vermont" />
	<Status StateCode="VA" StateName="Virginia" />
	<Status StateCode="WA" StateName="Washington" />
	<Status StateCode="WV" StateName="West Virginia" />
	<Status StateCode="WI" StateName="Wisconsin" />
	<Status StateCode="WY" StateName="Wyoming" />
</Status>
